microcosm_metrics/__init__.py
microcosm_metrics/classifier.py
microcosm_metrics/decorators.py
microcosm_metrics/factories.py
microcosm_metrics/main.py
microcosm_metrics/naming.py
microcosm_metrics-3.0.0.dist-info/LICENSE
microcosm_metrics-3.0.0.dist-info/METADATA
microcosm_metrics-3.0.0.dist-info/WHEEL
microcosm_metrics-3.0.0.dist-info/entry_points.txt
microcosm_metrics-3.0.0.dist-info/top_level.txt
microcosm_metrics-3.0.0.dist-info/RECORD
